aenet/__init__.py
aenet/aen.py
aenet/aencv.py
aenet-0.3.0.dist-info/WHEEL
aenet-0.3.0.dist-info/METADATA
aenet-0.3.0.dist-info/RECORD
