Metadata-Version: 2.1
Name: aenet
Version: 0.3.0
Summary: 
Author: Shota Imaki
Author-email: shota.imaki@icloud.com
Requires-Python: >=3.7.0,<4.0.0
Classifier: Programming Language :: Python :: 3
Classifier: Programming Language :: Python :: 3.7
Classifier: Programming Language :: Python :: 3.8
Classifier: Programming Language :: Python :: 3.9
Requires-Dist: asgl (>=1.0.5,<2.0.0)
Requires-Dist: cvxpy (>=1.1.0,<2.0.0)
Requires-Dist: numpy (>=1.0.0,<2.0.0)
Requires-Dist: scikit-learn (>=0.24.0,<0.25.0)
